fastapi_openapi_plus/__init__.py
fastapi_openapi_plus/cli.py
fastapi_openapi_plus/constants.py
fastapi_openapi_plus/examples.py
fastapi_openapi_plus/fields.py
fastapi_openapi_plus/generators.py
fastapi_openapi_plus/params.py
fastapi_openapi_plus/py.typed
fastapi_openapi_plus/typed_helpers.py
fastapi_openapi_plus/validators.py
fastapi_openapi_plus-0.1.0.dist-info/licenses/LICENSE
fastapi_openapi_plus-0.1.0.dist-info/METADATA
fastapi_openapi_plus-0.1.0.dist-info/WHEEL
fastapi_openapi_plus-0.1.0.dist-info/entry_points.txt
fastapi_openapi_plus-0.1.0.dist-info/top_level.txt
fastapi_openapi_plus-0.1.0.dist-info/RECORD
