Metadata-Version: 2.4
Name: fastapi-openapi-plus
Version: 0.1.0
Summary: Library for simplifying OpenAPI documentation in FastAPI (parameters, schemas, examples)
Author-email: Igor Selivanov <seligoroff@gmail.com>
License: MIT
Project-URL: Homepage, https://github.com/seligoroff/fastapi-openapi-plus
Project-URL: Repository, https://github.com/seligoroff/fastapi-openapi-plus
Project-URL: Issues, https://github.com/seligoroff/fastapi-openapi-plus/issues
Keywords: fastapi,openapi,documentation,api,swagger
Classifier: Development Status :: 3 - Alpha
Classifier: Intended Audience :: Developers
Classifier: License :: OSI Approved :: MIT License
Classifier: Programming Language :: Python :: 3
Classifier: Programming Language :: Python :: 3.8
Classifier: Programming Language :: Python :: 3.9
Classifier: Programming Language :: Python :: 3.10
Classifier: Programming Language :: Python :: 3.11
Classifier: Framework :: FastAPI
Requires-Python: >=3.8
License-File: LICENSE
Requires-Dist: fastapi>=0.104.0
Requires-Dist: pydantic>=1.10.0
Provides-Extra: dev
Requires-Dist: pytest>=7.4.0; extra == "dev"
Requires-Dist: pytest-asyncio>=0.21.0; extra == "dev"
Requires-Dist: pytest-cov>=4.1.0; extra == "dev"
Requires-Dist: black>=23.0.0; extra == "dev"
Requires-Dist: ruff>=0.1.0; extra == "dev"
Requires-Dist: mypy>=1.0.0; extra == "dev"
Provides-Extra: audit
Requires-Dist: click>=8.0.0; extra == "audit"
Dynamic: license-file
